rsskey.py
rsskey-0.2.0.dist-info/COPYING
rsskey-0.2.0.dist-info/WHEEL
rsskey-0.2.0.dist-info/METADATA
rsskey-0.2.0.dist-info/RECORD
