Metadata-Version: 2.1
Name: rsskey
Version: 0.2.0
Summary: RSS feed mirror on Misskey
Keywords: rss,misskey
Author-email: Nguyễn Gia Phong <mcsinyx@disroot.org>
Maintainer-email: Nguyễn Gia Phong <mcsinyx@disroot.org>
Requires-Python: >=3.7
Classifier: Development Status :: 5 - Production/Stable
Classifier: Framework :: Trio
Classifier: Intended Audience :: System Administrators
Classifier: License :: OSI Approved :: GNU Affero General Public License v3 or later (AGPLv3+)
Classifier: Operating System :: OS Independent
Classifier: Programming Language :: Python
Classifier: Topic :: Utilities
Requires-Dist: feedparser
Requires-Dist: httpx
Requires-Dist: loca
Requires-Dist: markdownify
Requires-Dist: trio
Project-URL: SourceHut, https://sr.ht/~cnx/rsskey
